majorityvoting/MajorityVoting.py
majorityvoting/__init__.py
majorityvoting-0.1.5.dist-info/DESCRIPTION.rst
majorityvoting-0.1.5.dist-info/METADATA
majorityvoting-0.1.5.dist-info/RECORD
majorityvoting-0.1.5.dist-info/WHEEL
majorityvoting-0.1.5.dist-info/metadata.json
majorityvoting-0.1.5.dist-info/top_level.txt
