Metadata-Version: 2.0
Name: majorityvoting
Version: 0.1.5
Summary: Majority Judgement Voting tool (fit for sklearn, etc.)
Home-page: https://github.com/TPeterW/Probabilistic-Majority-Voting
Author: Tao Peter Wang
Author-email: peterwangtao0@hotmail.com
License: UNKNOWN
Download-URL: https://github.com/TPeterW/Probabilistic-Majority-Voting/tarball/0.1.5
Keywords: majority voting,sklearn,machine learning,probability,majority judgement
Platform: UNKNOWN
Requires-Dist: numpy
